vapor/__init__.py
vapor/__main__.py
vapor/fn.py
vapor/hooks.py
vapor/models.py
vapor/stack.py
vapor/utils.py
vapor-0.1.0.dist-info/LICENSE
vapor-0.1.0.dist-info/METADATA
vapor-0.1.0.dist-info/WHEEL
vapor-0.1.0.dist-info/entry_points.txt
vapor-0.1.0.dist-info/RECORD
